ShellCreator/Commands.py
ShellCreator/Completer.py
ShellCreator/Expressions.py
ShellCreator/Highlighter.py
ShellCreator/Indenter.py
ShellCreator/Shell.py
ShellCreator/__init__.py
ShellCreator/Utils/ColoredLogs.py
ShellCreator/Utils/Operators.py
ShellCreator/Utils/__init__.py
ShellCreator-0.5.1.dist-info/LICENSE
ShellCreator-0.5.1.dist-info/METADATA
ShellCreator-0.5.1.dist-info/WHEEL
ShellCreator-0.5.1.dist-info/top_level.txt
ShellCreator-0.5.1.dist-info/RECORD
