Metadata-Version: 2.1
Name: ShellCreator
Version: 0.5.1
Summary: A library to create command line interfaces.
Home-page: https://github.com/mewais/ShellCreator
Author: Mohammad Ewais
Author-email: mewais@ece.utoronto.ca
License: MIT
Platform: UNKNOWN
Classifier: Programming Language :: Python :: 3
Classifier: License :: OSI Approved :: MIT License
Classifier: Operating System :: OS Independent
Requires-Dist: Pygments (==2.6.1)
Requires-Dist: prompt-toolkit (==3.0.5)
Requires-Dist: docopt (==0.6.2)
Requires-Dist: pyparsing (==2.4.7)
